py2jupyter/__init__.py
py2jupyter/__main__.py
py2jupyter-0.4.dist-info/licenses/LICENSE
tests/__init__.py
tests/test_converter.py
tests/test_data/test_case_01.py
tests/test_data/test_case_02.py
tests/test_data/test_case_03.py
tests/test_data/test_case_04.py
tests/test_data/test_case_05.py
tests/test_data/test_case_06.py
py2jupyter-0.4.dist-info/METADATA
py2jupyter-0.4.dist-info/WHEEL
py2jupyter-0.4.dist-info/entry_points.txt
py2jupyter-0.4.dist-info/top_level.txt
py2jupyter-0.4.dist-info/RECORD
