Metadata-Version: 2.4
Name: py2jupyter
Version: 0.4
Summary: Конвертер Python ↔ Jupyter Notebook
Author-email: Artem Antonov <artmihant@gmail.com>
Maintainer-email: Artem Antonov <artmihant@gmail.com>
License-Expression: MIT
Project-URL: Homepage, https://github.com/artmihant/py2jupyter
Project-URL: Documentation, https://github.com/artmihant/py2jupyter#readme
Project-URL: Repository, https://github.com/artmihant/py2jupyter.git
Keywords: jupyter,notebook,python,converter,markdown
Classifier: Development Status :: 4 - Beta
Classifier: Intended Audience :: Developers
Classifier: Intended Audience :: Science/Research
Classifier: Programming Language :: Python :: 3
Classifier: Programming Language :: Python :: 3.7
Classifier: Programming Language :: Python :: 3.8
Classifier: Programming Language :: Python :: 3.9
Classifier: Programming Language :: Python :: 3.10
Classifier: Programming Language :: Python :: 3.11
Classifier: Programming Language :: Python :: 3.12
Classifier: Topic :: Software Development :: Libraries :: Python Modules
Classifier: Topic :: Text Processing :: Markup
Requires-Python: >=3.7
License-File: LICENSE
Provides-Extra: dev
Requires-Dist: pytest>=7.0.0; extra == "dev"
Requires-Dist: pytest-cov>=4.0.0; extra == "dev"
Dynamic: license-file
